hamoodsquareroot-0.1.0.dist-info/licenses/LICENSE
square_root_lib/__init__.py
square_root_lib/__main__.py
square_root_lib/core.py
hamoodsquareroot-0.1.0.dist-info/METADATA
hamoodsquareroot-0.1.0.dist-info/WHEEL
hamoodsquareroot-0.1.0.dist-info/entry_points.txt
hamoodsquareroot-0.1.0.dist-info/top_level.txt
hamoodsquareroot-0.1.0.dist-info/RECORD
