Metadata-Version: 2.4
Name: HamoodSquareRoot
Version: 0.1.0
Summary: Calculate the square root of a number
Author: Hamood Ali Albukhaiti
Author-email: Hamood Ali Albukhaiti <hamoodalbukhity2000@gmail.com>
License: MIT License
Requires-Python: >=3.7
License-File: LICENSE
Dynamic: author
Dynamic: license-file
Dynamic: requires-python
